blockchaintxtools/__init__.py
blockchaintxtools/main.py
blockchaintxtools-0.1.1.dist-info/LICENSE
blockchaintxtools-0.1.1.dist-info/METADATA
blockchaintxtools-0.1.1.dist-info/WHEEL
blockchaintxtools-0.1.1.dist-info/top_level.txt
blockchaintxtools-0.1.1.dist-info/RECORD
