Metadata-Version: 2.1
Name: blockchaintxtools
Version: 0.1.1
Summary: A comprehensive toolkit for collecting, analyzing, filtering, and exporting blockchain transactions using Blockchair's database dumps.
Home-page: https://github.com/yorkeccak/blockchaintxtools
Author: Harvey Yorke
Author-email: harvey@valyu.network
Classifier: Development Status :: 3 - Alpha
Classifier: Intended Audience :: Developers
Classifier: License :: OSI Approved :: MIT License
Classifier: Operating System :: OS Independent
Classifier: Programming Language :: Python :: 3
Classifier: Programming Language :: Python :: 3.7
Classifier: Programming Language :: Python :: 3.8
Classifier: Programming Language :: Python :: 3.9
Classifier: Programming Language :: Python :: 3.10
Classifier: Programming Language :: Python :: 3.11
Classifier: Programming Language :: Python :: 3.12
Requires-Python: >=3.7
License-File: LICENSE
Requires-Dist: requests
Requires-Dist: pandas
Requires-Dist: tqdm
Requires-Dist: pydantic
Requires-Dist: python-dotenv
